rs_fastapi_utils/api_model.py
rs_fastapi_utils/api_settings.py
rs_fastapi_utils/camelcase.py
rs_fastapi_utils/cbv.py
rs_fastapi_utils/enums.py
rs_fastapi_utils/guid_type.py
rs_fastapi_utils/inferring_router.py
rs_fastapi_utils/openapi.py
rs_fastapi_utils/py.typed
rs_fastapi_utils/session.py
rs_fastapi_utils/tasks.py
rs_fastapi_utils/timing.py
rs_fastapi_utils-0.4.0.dist-info/LICENSE
rs_fastapi_utils-0.4.0.dist-info/METADATA
rs_fastapi_utils-0.4.0.dist-info/WHEEL
rs_fastapi_utils-0.4.0.dist-info/RECORD
