Metadata-Version: 2.1
Name: rs-fastapi-utils
Version: 0.4.0
Summary: Reusable utilities for FastAPI
Home-page: https://gitlab.com/rocshers/python/rs-fastapi-utils
License: MIT
Keywords: fastapi,utilities,utils
Author: rocshers
Author-email: develop@rocshers.com
Requires-Python: >=3.8,<4.0
Classifier: Development Status :: 3 - Alpha
Classifier: Environment :: Web Environment
Classifier: Framework :: AsyncIO
Classifier: Intended Audience :: Developers
Classifier: Intended Audience :: Information Technology
Classifier: Intended Audience :: System Administrators
Classifier: License :: OSI Approved :: MIT License
Classifier: Operating System :: OS Independent
Classifier: Programming Language :: Python
Classifier: Programming Language :: Python :: 3
Classifier: Programming Language :: Python :: 3.8
Classifier: Programming Language :: Python :: 3.9
Classifier: Programming Language :: Python :: 3.10
Classifier: Programming Language :: Python :: 3.11
Classifier: Programming Language :: Python :: 3
Classifier: Programming Language :: Python :: 3 :: Only
Classifier: Programming Language :: Python :: 3.10
Classifier: Programming Language :: Python :: 3.11
Classifier: Programming Language :: Python :: 3.8
Classifier: Programming Language :: Python :: 3.9
Classifier: Topic :: Internet
Classifier: Topic :: Internet :: WWW/HTTP
Classifier: Topic :: Internet :: WWW/HTTP :: HTTP Servers
Classifier: Topic :: Software Development
Classifier: Topic :: Software Development :: Libraries
Classifier: Topic :: Software Development :: Libraries :: Python Modules
Classifier: Topic :: Utilities
Classifier: Typing :: Typed
Requires-Dist: fastapi (>=0,<1)
Requires-Dist: pydantic (>=1,<2)
Requires-Dist: sqlalchemy (>=2,<3)
Project-URL: Documentation, https://rs-fastapi-utils.docs.rocshers.com
Project-URL: Repository, https://gitlab.com/rocshers/python/rs-fastapi-utils
